{
  "imagePath": "../assets/page23.avif",
  "dimensions": {
    "width": 2760,
    "height": 3837
  },
  "panels": [
    {
      "id": 0,
      "x": 52,
      "y": 101,
      "width": 1649,
      "height": 872
    },
    {
      "id": 1,
      "x": 1734,
      "y": 127,
      "width": 959,
      "height": 845
    },
    {
      "id": 2,
      "x": 38,
      "y": 1005,
      "width": 868,
      "height": 871
    },
    {
      "id": 3,
      "x": 935,
      "y": 1011,
      "width": 868,
      "height": 867
    },
    {
      "id": 4,
      "x": 1840,
      "y": 1017,
      "width": 858,
      "height": 388
    },
    {
      "id": 5,
      "x": 1840,
      "y": 1418,
      "width": 868,
      "height": 458
    },
    {
      "id": 6,
      "x": 30,
      "y": 1922,
      "width": 919,
      "height": 877
    },
    {
      "id": 7,
      "x": 976,
      "y": 1925,
      "width": 850,
      "height": 870
    },
    {
      "id": 8,
      "x": 1830,
      "y": 1924,
      "width": 882,
      "height": 874
    },
    {
      "id": 9,
      "x": 23,
      "y": 2838,
      "width": 959,
      "height": 887
    },
    {
      "id": 10,
      "x": 1012,
      "y": 2844,
      "width": 729,
      "height": 881
    },
    {
      "id": 11,
      "x": 1773,
      "y": 2845,
      "width": 950,
      "height": 886
    }
  ],
  "metadata": {
    "extractedAt": "2025-12-11T04:25:14.720Z"
  }
}